setup.py
src/xooof/__init__.py
src/xooof.spectools.egg-info/PKG-INFO
src/xooof.spectools.egg-info/SOURCES.txt
src/xooof.spectools.egg-info/dependency_links.txt
src/xooof.spectools.egg-info/entry_points.txt
src/xooof.spectools.egg-info/namespace_packages.txt
src/xooof.spectools.egg-info/not-zip-safe
src/xooof.spectools.egg-info/requires.txt
src/xooof.spectools.egg-info/top_level.txt
src/xooof/spectools/__init__.py
src/xooof/spectools/class2OM.py
src/xooof/spectools/classOM.py
src/xooof/spectools/classns2OM.py
src/xooof/spectools/classnsOM.py
src/xooof/spectools/commonOM.py
src/xooof/spectools/fsm2OM.py
src/xooof/spectools/fsmOM.py
src/xooof/spectools/interface2OM.py
src/xooof/spectools/interfaceOM.py
src/xooof/spectools/interfacens2OM.py
src/xooof/spectools/interfacensOM.py
src/xooof/spectools/struct2OM.py
src/xooof/spectools/structOM.py
src/xooof/spectools/structns2OM.py
src/xooof/spectools/structnsOM.py
src/xooof/spectools/tests/__init__.py
src/xooof/spectools/tests/tests.py