Metadata-Version: 1.0
Name: xooof.spectools
Version: 0.1
Summary: The spectools parts of the xooof runtime development tools for python
Home-page: http://sourceforge.net/projects/xooof/
Author: Stephane Bidoul, Laurent Mignon
Author-email: laurent.mignon__at__softwareag.com
License: GNU Lesser General Public License
Platform: UNKNOWN
Classifier: Programming Language :: Python
Classifier: Topic :: Software Development :: Libraries :: Python Modules
